thqml/EntangledFeatureMap.py
thqml/__init__.py
thqml/phasespace.py
thqml/quantummap.py
thqml/quantumsolitons.py
thqml/utilities.py
thqml-1.0.0.dist-info/METADATA
thqml-1.0.0.dist-info/WHEEL
thqml-1.0.0.dist-info/licenses/LICENSE.txt
thqml-1.0.0.dist-info/RECORD
