Metadata-Version: 2.1
Name: thqml
Version: 1.0.0
Summary: Thinking Quantum Machine Learning, code of the book Quantum Machine Learning
Author-email: Claudio Conti <nonlinearxwaves@gmail.com>
License: 3-Clause BSD License
License-File: LICENSE.txt
Classifier: License :: OSI Approved :: BSD License
Classifier: Operating System :: OS Independent
Classifier: Programming Language :: Python
Requires-Python: >=3.10
Requires-Dist: jupyter
Requires-Dist: keras
Requires-Dist: keras-utils
Requires-Dist: matplotlib
Requires-Dist: numpy
Requires-Dist: pydot
Requires-Dist: qutip
Requires-Dist: scikit-learn
Requires-Dist: tdqm
Requires-Dist: tensorflow-addons
Requires-Dist: tensorflow==2.11.0
Requires-Dist: typing-extensions
